MANIFEST.in
README.md
README.rst
setup.py
binario/__init__.py
binario/byte_order.py
binario/reader.py
binario/writer.py
binario.egg-info/PKG-INFO
binario.egg-info/SOURCES.txt
binario.egg-info/dependency_links.txt
binario.egg-info/not-zip-safe
binario.egg-info/top_level.txt