Metadata-Version: 1.1
Name: binario
Version: 0.0.4
Summary: Package that lets an application read/write primitive data types from an underlying input/output stream as binary data.
Home-page: http://github.com/asaskevich/binario
Author: Alex Saskevich
Author-email: bwatas@gmail.com
License: MIT
Download-URL: https://pypi.python.org/pypi/binario
Keywords: io input output file binary binario data
Platform: UNKNOWN
Classifier: Development Status :: 3 - Alpha
Classifier: Programming Language :: Python :: 3
Classifier: Programming Language :: Python :: 3.0
Classifier: Programming Language :: Python :: 3.1
Classifier: Programming Language :: Python :: 3.2
Classifier: Programming Language :: Python :: 3.3
Classifier: Programming Language :: Python :: 3.4
Classifier: Topic :: Software Development :: Libraries
Classifier: Topic :: Software Development :: Libraries :: Python Modules
Classifier: Topic :: System
Classifier: Topic :: System :: Filesystems
Classifier: Topic :: Utilities
